src/__init__.py
src/client.py
src/config.py
src/exceptions.py
src/implementations.py
src/protocols.py
src/models/__init__.py
src/models/brand_models.py
src/models/common_models.py
src/models/product_models.py
src/models/search_models.py
src/models/seller_models.py
src/services/__init__.py
src/services/base.py
src/services/brands.py
src/services/products.py
src/services/sellers.py
digikala_sdk-1.0.0.dist-info/METADATA
digikala_sdk-1.0.0.dist-info/WHEEL
digikala_sdk-1.0.0.dist-info/top_level.txt
digikala_sdk-1.0.0.dist-info/RECORD
