Metadata-Version: 2.4
Name: digikala-sdk
Version: 1.0.0
Summary: Asynchronous Python SDK for Digikala API
Author-email: Digikala SDK Team <sdk@digikala.com>
License: MIT
Project-URL: Homepage, https://github.com/digikala/digikala-sdk
Project-URL: Documentation, https://docs.digikala.com/sdk
Project-URL: Repository, https://github.com/digikala/digikala-sdk
Project-URL: Issues, https://github.com/digikala/digikala-sdk/issues
Classifier: Development Status :: 5 - Production/Stable
Classifier: Intended Audience :: Developers
Classifier: License :: OSI Approved :: MIT License
Classifier: Programming Language :: Python :: 3
Classifier: Programming Language :: Python :: 3.8
Classifier: Programming Language :: Python :: 3.9
Classifier: Programming Language :: Python :: 3.10
Classifier: Programming Language :: Python :: 3.11
Classifier: Programming Language :: Python :: 3.12
Classifier: Framework :: AsyncIO
Classifier: Framework :: FastAPI
Classifier: Topic :: Software Development :: Libraries :: Python Modules
Requires-Python: >=3.8
Requires-Dist: httpx>=0.24.0
Requires-Dist: pydantic>=2.0.0
Provides-Extra: dev
Requires-Dist: pytest>=7.0.0; extra == "dev"
Requires-Dist: pytest-asyncio>=0.21.0; extra == "dev"
Requires-Dist: respx>=0.20.0; extra == "dev"
Requires-Dist: pytest-cov>=4.0.0; extra == "dev"
Provides-Extra: fastapi
Requires-Dist: fastapi>=0.100.0; extra == "fastapi"
Requires-Dist: uvicorn>=0.23.0; extra == "fastapi"
Provides-Extra: cache
Requires-Dist: aiocache>=0.12.0; extra == "cache"
Provides-Extra: ratelimit
Requires-Dist: aiolimiter>=1.1.0; extra == "ratelimit"
Provides-Extra: full
Requires-Dist: aiocache>=0.12.0; extra == "full"
Requires-Dist: aiolimiter>=1.1.0; extra == "full"
